MesaSoapManager/__init__.py
MesaSoapManager/nav_soap_client.py
ODCHelperFunctions/__init__.py
ODCHelperFunctions/helpers.py
PaligoClient/__init__.py
PaligoClient/paligoclient.py
mesa_solutions_utils-1.1.12.dist-info/LICENSE
mesa_solutions_utils-1.1.12.dist-info/METADATA
mesa_solutions_utils-1.1.12.dist-info/WHEEL
mesa_solutions_utils-1.1.12.dist-info/top_level.txt
mesa_solutions_utils-1.1.12.dist-info/RECORD
