Metadata-Version: 2.1
Name: mesa-solutions-utils
Version: 1.1.12
Summary: Various utilities functions and classes
Home-page: https://dev.azure.com/mesa-ngs/_git/mesa-solutions-utils
Author: Mesa Natural Gas Solutions, LLC
Author-email: support@mesangs.com
License: MIT
Download-URL: https://dev.azure.com/mesa-ngs/_git/mesa-solutions-utils
Keywords: Microsoft Dynamics NAV,PaligoSOAP
Platform: UNKNOWN
Requires-Dist: zeep (<4,>=3)
Requires-Dist: requests (<3,>=2)
